listlookup/__init__.py
listlookup/__version__.py
listlookup/listlookup.py
list_lookup-1.0.7.dist-info/LICENSE
list_lookup-1.0.7.dist-info/METADATA
list_lookup-1.0.7.dist-info/WHEEL
list_lookup-1.0.7.dist-info/top_level.txt
list_lookup-1.0.7.dist-info/RECORD
