Metadata-Version: 2.1
Name: list-lookup
Version: 1.0.7
Summary: Wrapper for a list of objects that allows to create indexes for faster lookups 
Home-page: https://github.com/gluk-w/python-list-lookup
Author: Stan Misiurev
Author-email: smisiurev@gmail.com
License: MIT
Keywords: lookup indexing list
Platform: UNKNOWN
Classifier: Programming Language :: Python :: 2
Classifier: Programming Language :: Python :: 2.7
Classifier: Programming Language :: Python :: 3
Classifier: Programming Language :: Python :: 3.4
Classifier: Programming Language :: Python :: 3.5
Classifier: Programming Language :: Python :: 3.6
Requires-Dist: setuptools
